pydetailtools/__init__.py
pydetailtools/string.py
py_detail_tools-1.0.1.dist-info/METADATA
py_detail_tools-1.0.1.dist-info/WHEEL
py_detail_tools-1.0.1.dist-info/top_level.txt
py_detail_tools-1.0.1.dist-info/RECORD
